LICENCE
continuous_timeseries-0.4.3.dist-info/METADATA
continuous_timeseries-0.4.3.dist-info/WHEEL
continuous_timeseries-0.4.3.dist-info/entry_points.txt
continuous_timeseries-0.4.3.dist-info/licenses/LICENCE
continuous_timeseries/__init__.py
continuous_timeseries/budget_compatible_pathways.py
continuous_timeseries/discrete_to_continuous/__init__.py
continuous_timeseries/discrete_to_continuous/higher_order.py
continuous_timeseries/discrete_to_continuous/interpolation_option.py
continuous_timeseries/discrete_to_continuous/linear.py
continuous_timeseries/discrete_to_continuous/piecewise_constant_common.py
continuous_timeseries/discrete_to_continuous/piecewise_constant_next_left_closed.py
continuous_timeseries/discrete_to_continuous/piecewise_constant_next_left_open.py
continuous_timeseries/discrete_to_continuous/piecewise_constant_previous_left_closed.py
continuous_timeseries/discrete_to_continuous/piecewise_constant_previous_left_open.py
continuous_timeseries/domain_helpers.py
continuous_timeseries/exceptions.py
continuous_timeseries/formatting.py
continuous_timeseries/pandas_accessors.py
continuous_timeseries/plotting_helpers.py
continuous_timeseries/py.typed
continuous_timeseries/time_axis.py
continuous_timeseries/timeseries.py
continuous_timeseries/timeseries_continuous.py
continuous_timeseries/timeseries_discrete.py
continuous_timeseries/typing.py
continuous_timeseries/values_at_bounds.py
continuous_timeseries/warnings.py
continuous_timeseries-0.4.3.dist-info/RECORD
