Metadata-Version: 2.1
Name: continuous-timeseries
Version: 0.4.3
Summary: Representation of continuous timeseries.
Author-Email: Zebedee Nicholls <zebedee.nicholls@climate-energy-college.org>
License: 3-Clause BSD License
Classifier: Development Status :: 4 - Beta
Classifier: Intended Audience :: Science/Research
Classifier: License :: OSI Approved :: BSD License
Classifier: Natural Language :: English
Classifier: Operating System :: OS Independent
Classifier: Programming Language :: Python
Classifier: Programming Language :: Python :: 3
Classifier: Programming Language :: Python :: 3 :: Only
Classifier: Programming Language :: Python :: 3.9
Classifier: Programming Language :: Python :: 3.10
Classifier: Programming Language :: Python :: 3.11
Classifier: Programming Language :: Python :: 3.12
Classifier: Programming Language :: Python :: 3.13
Classifier: Typing :: Typed
Project-URL: Homepage, https://continuous-timeseries.readthedocs.io
Project-URL: Documentation, https://continuous-timeseries.readthedocs.io
Project-URL: Changelog, https://continuous-timeseries.readthedocs.io/en/stable/changelog
Project-URL: Repository, https://github.com/openscm/continuous-timeseries
Project-URL: Issues, https://github.com/openscm/continuous-timeseries/issues
Requires-Python: >=3.9
Requires-Dist: attrs>=22.1.0
Requires-Dist: numpy>=1.25.0
Requires-Dist: pint>=0.22.0
Provides-Extra: pandas
Requires-Dist: pandas>=2.0.0; extra == "pandas"
Provides-Extra: plots
Requires-Dist: matplotlib>=3.7.1; extra == "plots"
Provides-Extra: progress
Requires-Dist: tqdm>=4.1.0; extra == "progress"
Provides-Extra: scipy
Requires-Dist: scipy>=1.11.1; extra == "scipy"
Provides-Extra: full
Requires-Dist: continuous-timeseries[pandas]; extra == "full"
Requires-Dist: continuous-timeseries[plots]; extra == "full"
Requires-Dist: continuous-timeseries[progress]; extra == "full"
Requires-Dist: continuous-timeseries[scipy]; extra == "full"
Provides-Extra: locked
Requires-Dist: attrs==24.3.0; extra == "locked"
Requires-Dist: flexcache==0.3; extra == "locked"
Requires-Dist: flexparser==0.4; extra == "locked"
Requires-Dist: numpy==2.0.2; extra == "locked"
Requires-Dist: pint==0.24.4; extra == "locked"
Requires-Dist: platformdirs==4.3.7; extra == "locked"
Requires-Dist: typing-extensions==4.13.2; extra == "locked"
Provides-Extra: pandas-locked
Requires-Dist: numpy==2.0.2; extra == "pandas-locked"
Requires-Dist: pandas==2.2.3; extra == "pandas-locked"
Requires-Dist: python-dateutil==2.9.0.post0; extra == "pandas-locked"
Requires-Dist: pytz==2025.2; extra == "pandas-locked"
Requires-Dist: six==1.17.0; extra == "pandas-locked"
Requires-Dist: tzdata==2025.2; extra == "pandas-locked"
Provides-Extra: plots-locked
Requires-Dist: contourpy==1.3.0; extra == "plots-locked"
Requires-Dist: cycler==0.12.1; extra == "plots-locked"
Requires-Dist: fonttools==4.57.0; extra == "plots-locked"
Requires-Dist: importlib-resources==6.5.2; python_version < "3.10" and extra == "plots-locked"
Requires-Dist: kiwisolver==1.4.7; extra == "plots-locked"
Requires-Dist: matplotlib==3.9.4; extra == "plots-locked"
Requires-Dist: numpy==2.0.2; extra == "plots-locked"
Requires-Dist: packaging==24.2; extra == "plots-locked"
Requires-Dist: pillow==11.2.1; extra == "plots-locked"
Requires-Dist: pyparsing==3.2.3; extra == "plots-locked"
Requires-Dist: python-dateutil==2.9.0.post0; extra == "plots-locked"
Requires-Dist: six==1.17.0; extra == "plots-locked"
Requires-Dist: zipp==3.21.0; python_version < "3.10" and extra == "plots-locked"
Provides-Extra: progress-locked
Requires-Dist: colorama==0.4.6; extra == "progress-locked"
Requires-Dist: tqdm==4.67.1; extra == "progress-locked"
Provides-Extra: scipy-locked
Requires-Dist: numpy==2.0.2; extra == "scipy-locked"
Requires-Dist: scipy==1.13.1; extra == "scipy-locked"
Provides-Extra: full-locked
Requires-Dist: colorama==0.4.6; extra == "full-locked"
Requires-Dist: contourpy==1.3.0; extra == "full-locked"
Requires-Dist: cycler==0.12.1; extra == "full-locked"
Requires-Dist: fonttools==4.57.0; extra == "full-locked"
Requires-Dist: importlib-resources==6.5.2; python_version < "3.10" and extra == "full-locked"
Requires-Dist: kiwisolver==1.4.7; extra == "full-locked"
Requires-Dist: matplotlib==3.9.4; extra == "full-locked"
Requires-Dist: numpy==2.0.2; extra == "full-locked"
Requires-Dist: packaging==24.2; extra == "full-locked"
Requires-Dist: pandas==2.2.3; extra == "full-locked"
Requires-Dist: pillow==11.2.1; extra == "full-locked"
Requires-Dist: pyparsing==3.2.3; extra == "full-locked"
Requires-Dist: python-dateutil==2.9.0.post0; extra == "full-locked"
Requires-Dist: pytz==2025.2; extra == "full-locked"
Requires-Dist: scipy==1.13.1; extra == "full-locked"
Requires-Dist: six==1.17.0; extra == "full-locked"
Requires-Dist: tqdm==4.67.1; extra == "full-locked"
Requires-Dist: tzdata==2025.2; extra == "full-locked"
Requires-Dist: zipp==3.21.0; python_version < "3.10" and extra == "full-locked"
